[{"str":0,"class":1,"acc":2,"dex":0,"level":1,"matk":1,"hpPlv":[10,15,20],"matkPlv":[0.1,0.2,0.3],"atk":5,"passiveList":["Might","Vitality","Juggernaut"],"defPlv":[1.2,1.6,2],"name":"Warrior","skillList":["Slash","Shield Slam","Block","Slash II","Unbreakable","Shield Slam II","Taunt"],"accPlv":[0.3,0.6,0.9],"crit":1,"strMod":[5,7,10],"expMod":0,"hp":100,"desc1":"A strong tank with","critPlv":[0,0,0],"mdef":8,"mdefPlv":[0.4,0.8,1.2],"def":14,"defaultHeroInventory":["Worn Sword","Worn Helm","Worn Vest","Worn Gloves","Worn Boots","Worn Trinket"],"intMod":[1,1,1],"exp":0,"defaultAttackList":["Basic","Basic","Basic","Basic","Basic"],"lockedDesc":"","desc2":"high defense","atkPlv":[0.4,0.8,1.2],"dexMod":[4,6,7],"int":0,"lckMod":0},{"str":0,"class":2,"acc":2,"dex":0,"level":1,"matk":1,"hpPlv":[8,12,14],"matkPlv":[0.1,0.2,0.3],"atk":5,"passiveList":["Might","Keen Eye","Critical Strike"],"defPlv":[0.5,1,1.5],"name":"Rogue","skillList":["Kidney Shot","Sunder","Cheap Shot","Evade","Kidney Shot II","Cheap Shot II","Counter Attack"],"accPlv":[0.5,1,1.5],"crit":5,"strMod":[4,6,8],"expMod":0,"hp":90,"desc1":"A nimble fighter with","critPlv":[0.2,0.2,0.3],"mdef":8,"mdefPlv":[0.4,0.8,1.2],"def":9,"defaultHeroInventory":["Worn Sword","Worn Helm","Worn Vest","Worn Gloves","Worn Boots","Worn Trinket"],"intMod":[1,1,1],"exp":0,"defaultAttackList":["Basic","Basic","Basic","Basic","Basic"],"lockedDesc":"","desc2":"high accuracy","atkPlv":[0.6,1.2,1.8],"dexMod":[5,8,10],"int":0,"lckMod":0},{"str":0,"class":3,"acc":2,"dex":0,"level":1,"matk":5,"hpPlv":[7,11,14],"matkPlv":[0.9,1.8,2.8],"atk":1,"passiveList":["Intellect","Wisdom","Mind"],"defPlv":[0.4,0.8,1.2],"name":"Mage","skillList":["Mind Blast","Magic Missile","Mind Blast II","Mana Shield","Silence","Magic Missile II","Mana Shield II"],"accPlv":[0.3,0.6,0.9],"crit":1,"strMod":[1,1,1],"expMod":0,"hp":80,"desc1":"A powerful wizard with","critPlv":[0,0,0],"mdef":10,"mdefPlv":[0.4,0.8,1.2],"def":7,"defaultHeroInventory":["Worn Stave","Worn Helm","Worn Vest","Worn Gloves","Worn Boots","Worn Trinket"],"intMod":[6,9,12],"exp":0,"defaultAttackList":["Basic","Basic","Basic","Basic","Basic"],"lockedDesc":"","desc2":"high magic attack","atkPlv":[0.1,0.2,0.3],"dexMod":[3,5,6],"int":0,"lckMod":0},{"str":0,"class":4,"acc":2,"dex":0,"level":1,"matk":1,"hpPlv":[8,12,16],"matkPlv":[0.1,0.2,0.3],"atk":5,"passiveList":["Might","Critical Eye","Critical Strike"],"defPlv":[0.5,1,1.5],"name":"Berserker","skillList":["Slash","Enrage","Slash II","Vicious Strike","Blind Fury","Vicious Strike II","Berserk Rage"],"accPlv":[0.3,0.6,0.9],"crit":1,"strMod":[6,9,12],"expMod":0,"hp":90,"desc1":"A mighty warrior with","critPlv":[0,0,0],"mdef":7,"mdefPlv":[0.4,0.8,1.2],"def":10,"defaultHeroInventory":["Worn Hatchet","Worn Helm","Worn Vest","Worn Gloves","Worn Boots","Worn Trinket"],"intMod":[1,1,1],"exp":0,"defaultAttackList":["Basic","Basic","Basic","Basic","Basic"],"lockedDesc":"Unlocked at Lv 15 War","desc2":"high attack","atkPlv":[0.8,1.6,2.4],"dexMod":[3,5,7],"int":0,"lckMod":0},{"str":0,"class":5,"acc":2,"dex":0,"level":1,"matk":5,"hpPlv":[7,11,14],"matkPlv":[0.6,1.2,1.8],"atk":1,"passiveList":["Intellect","Wisdom","Mind"],"defPlv":[0.4,0.8,1.2],"name":"Cleric","skillList":["Mind Blast","Divine Strike","Mind Blast II","Lesser Heal","Cleanse","Greater Heal","Revive"],"accPlv":[0.6,1.2,1.8],"crit":1,"strMod":[1,1,1],"expMod":0,"hp":80,"desc1":"A wise priest with","critPlv":[0,0,0],"mdef":10,"mdefPlv":[0.4,0.8,1.2],"def":7,"defaultHeroInventory":["Worn Wand","Worn Helm","Worn Vest","Worn Gloves","Worn Boots","Worn Trinket"],"intMod":[5,8,11],"exp":0,"defaultAttackList":["Basic","Basic","Basic","Basic","Basic"],"lockedDesc":"Unlocked at Lv 15 Mag","desc2":"high accuracy","atkPlv":[0.1,0.2,0.3],"dexMod":[4,6,8],"int":0,"lckMod":0},{"str":0,"class":6,"acc":2,"dex":0,"level":1,"matk":1,"hpPlv":[8,12,16],"matkPlv":[0.1,0.2,0.3],"atk":5,"passiveList":["Keen Eye","Critical Eye","Critical Strike"],"defPlv":[0.5,1,1.5],"name":"Assassin","skillList":["Kidney Shot","Stab","Puncture","Evade","Stab II","Puncture II","Detect Weakness"],"accPlv":[0.6,1.2,1.8],"crit":10,"strMod":[3,5,7],"expMod":0,"hp":90,"desc1":"A deadly ninja with","critPlv":[0.2,0.4,0.7],"mdef":8,"mdefPlv":[0.4,0.8,1.2],"def":9,"defaultHeroInventory":["Worn Sword","Worn Helm","Worn Vest","Worn Gloves","Worn Boots","Worn Trinket"],"intMod":[1,1,1],"exp":0,"defaultAttackList":["Basic","Basic","Basic","Basic","Basic"],"lockedDesc":"Unlocked at Lv 15 Rog","desc2":"high crit","atkPlv":[0.5,1,1.6],"dexMod":[6,7,9],"int":0,"lckMod":0},{"str":0,"class":7,"acc":2,"dex":0,"level":1,"matk":3,"hpPlv":[10,15,20],"matkPlv":[0.3,0.6,0.9],"atk":3,"passiveList":["Mind","Vitality","Juggernaut"],"defPlv":[0.4,0.8,1.2],"name":"Paladin","skillList":["Slash","Divine Strike","Shield","Protect","Unbreakable","Divine Strike II","Holy Shield"],"accPlv":[0.3,0.6,0.9],"crit":1,"strMod":[3,5,8],"expMod":0,"hp":100,"desc1":"A sturdy tank with","critPlv":[0,0,0],"mdef":14,"mdefPlv":[1,2,3],"def":8,"defaultHeroInventory":["Worn Sword","Worn Helm","Worn Vest","Worn Gloves","Worn Boots","Worn Trinket"],"intMod":[3,5,8],"exp":0,"defaultAttackList":["Basic","Basic","Basic","Basic","Basic"],"lockedDesc":"Unlocked at ???","desc2":"high magic defense","atkPlv":[0.3,0.6,0.9],"dexMod":[3,5,7],"int":0,"lckMod":0},{"str":0,"class":8,"acc":2,"dex":0,"level":1,"matk":3,"hpPlv":[7,11,15],"matkPlv":[0.4,0.8,1.2],"atk":3,"passiveList":["Might","Intellect","Wisdom"],"defPlv":[0.4,0.8,1.2],"name":"Dark Knight","skillList":["Dark Slash","Poison","Terrify","Overwhelm","Slow","Dark Slash II","Twilight Strike"],"accPlv":[0.3,0.7,1],"crit":1,"strMod":[5,7,10],"expMod":0,"hp":80,"desc1":"A powerful warlock","critPlv":[0,0,0],"mdef":9,"mdefPlv":[0.4,0.8,1.2],"def":10,"defaultHeroInventory":["Worn Club","Worn Helm","Worn Vest","Worn Gloves","Worn Boots","Worn Trinket"],"intMod":[5,7,10],"exp":0,"defaultAttackList":["Basic","Basic","Basic","Basic","Basic"],"lockedDesc":"Unlocked at ???","desc2":"with high damage","atkPlv":[0.4,0.8,1.2],"dexMod":[0,2,4],"int":0,"lckMod":0},{"str":0,"class":9,"acc":2,"dex":0,"level":1,"matk":2,"hpPlv":[7,13,18],"matkPlv":[0.3,0.6,0.9],"atk":2,"passiveList":["Consolidate","Juggernaut","Wisdom"],"defPlv":[0.2,0.4,1],"name":"Bard","skillList":["Serenade","Song of Courage","Master Decoy","Poem of Focus","Song of Defense","Peaceful Respite","Double Image","Recharge"],"accPlv":[0.3,0.7,1],"crit":1,"strMod":[2,5,8],"expMod":10,"hp":60,"desc1":"A chronicler","critPlv":[0.1,0.2,0.3],"mdef":6,"mdefPlv":[0.2,0.4,1],"def":6,"defaultHeroInventory":["Worn Club","Worn Helm","Worn Vest","Worn Gloves","Worn Boots","Worn Trinket"],"intMod":[2,5,8],"exp":0,"defaultAttackList":["Basic","Basic","Basic","Basic","Basic"],"lockedDesc":"Unlocked with Frozen Tome","desc2":"of adventures","atkPlv":[0.3,0.6,0.9],"dexMod":[2,5,8],"int":0,"lckMod":10}]